git_of_theseus/__init__.py
git_of_theseus/analyze.py
git_of_theseus/line_plot.py
git_of_theseus/stack_plot.py
git_of_theseus/survival_plot.py
git_of_theseus/utils.py
git_of_theseus-0.3.4.dist-info/LICENSE
git_of_theseus-0.3.4.dist-info/METADATA
git_of_theseus-0.3.4.dist-info/WHEEL
git_of_theseus-0.3.4.dist-info/entry_points.txt
git_of_theseus-0.3.4.dist-info/top_level.txt
git_of_theseus-0.3.4.dist-info/RECORD
